gradio_dataset/__init__.py
gradio_dataset/dataset.py
gradio_dataset/dataset.pyi
gradio_dataset/templates/component/index.js
gradio_dataset/templates/component/style.css
gradio_dataset-0.0.2.dist-info/METADATA
gradio_dataset-0.0.2.dist-info/WHEEL
gradio_dataset-0.0.2.dist-info/RECORD
