Metadata-Version: 2.3
Name: gradio_dataset
Version: 0.0.2
Summary: Python library for easily interacting with trained machine learning models
Author-email: thenHung <hung.le@mettadepth.com>
License-Expression: Apache-2.0
Keywords: gradio-custom-component,gradio-template-Dataset
Classifier: Development Status :: 3 - Alpha
Classifier: Operating System :: OS Independent
Classifier: Programming Language :: Python :: 3
Classifier: Programming Language :: Python :: 3 :: Only
Classifier: Programming Language :: Python :: 3.8
Classifier: Programming Language :: Python :: 3.9
Classifier: Programming Language :: Python :: 3.10
Classifier: Programming Language :: Python :: 3.11
Classifier: Topic :: Scientific/Engineering
Classifier: Topic :: Scientific/Engineering :: Artificial Intelligence
Classifier: Topic :: Scientific/Engineering :: Visualization
Requires-Python: >=3.8
Requires-Dist: gradio-modal-component<1.0,>=0.0.4
Requires-Dist: gradio<5.0,>=4.44.1
Provides-Extra: dev
Requires-Dist: build; extra == 'dev'
Requires-Dist: twine; extra == 'dev'
